whatweb.py
whatweb-0.0.7.dist-info/LICENSE
whatweb-0.0.7.dist-info/METADATA
whatweb-0.0.7.dist-info/WHEEL
whatweb-0.0.7.dist-info/entry_points.txt
whatweb-0.0.7.dist-info/top_level.txt
whatweb-0.0.7.dist-info/RECORD
