Metadata-Version: 2.1
Name: whatweb
Version: 0.0.7
Summary: Next generation web scanner
Home-page: https://github.com/jakbin/whatweb
Author: Jak Bin
Author-email: jakbin4747@gmail.com
Project-URL: Bug Tracker, https://github.com/jakbin/whatweb/issues
Keywords: whatweb,web-scanner
Classifier: Programming Language :: Python :: 3.6
Classifier: License :: OSI Approved :: MIT License
Classifier: Natural Language :: English
Classifier: Operating System :: OS Independent
Requires-Python: >=3
License-File: LICENSE
Requires-Dist: requests
Requires-Dist: beautifulsoup4
